{
	"metaDataVersion": "1.0.0",
	"category": "com.microchip.ide.project",
	"content": {
		"metaDataVersion": "1.1.0",
		"name": "com.microchip.mcu32.mplabx.project.net_apps_sam_a7g5_tcpip_tcp_server_sam_a7g5_ek_GMAC1_freertos",
		"version": "3.7.0",
		"displayName": "TCP/IP TCP Server Application Example for SAMA7G5 Family",
		"projectName": "tcpip_tcp_server_GMAC1_freertos",
		"shortDescription": "The TCP/IP TCP Server configuration demonstrates creating a network server that uses the MPLAB Harmony TCP API to create a TCP/IP echo server on port 9760.",
		"ide": {
			"name": "MPLABX",
			"semverRange": ">=6.00"
		},
		"compiler": [
			{
				"name": "XC32",
				"semverRange": ">=4.00"
			}
		],
		"dfp": {
			"name": "SAMA7G5_DFP",
			"semverRange": "^1.0.56"
		},
		"configurator": {
			"name": "MCC",
			"semverRange": ">=5.2.0"
		},
		"device": {
			"metaDataVersion": "1.0.0",
			"category": "com.microchip.portal.contentRef",
			"content": {
				"metaDataVersion": "1.0.0",
				"category": "com.microchip.device",
				"name": "SAMA7G54",
				"versionRange": "*"
			}
		},
		"author": "Microchip",
		"subcategories": [
			[
				"Development Kit", "SAMA7G54-EK"
			],
			[
				"Harmony", "Middleware", "TCP/IP", "TCPIP_TCP_SERVER"
			],
			[
				"Middleware", "TCP/IP", "TCPIP_TCP_SERVER"
			]
		],
		"peripherals": [
			"MAC"
		],
		"keywords": [
			"MHC",
			"Harmony",
			"Middleware",
			"TCP/IP",
			"SAMA7G54",
			"SAMA7G5 Family",
			"Ethernet MAC",
			"GMAC"
		],
		"additionalData": {
			"longDescription": {
				"metaDataVersion": "1.0.0",
				"category": "com.microchip.portal.fileRef",
				"content": {
					"metaDataVersion": "1.0.0",
					"fileName": "./../../readme.md",
					"mimeType": "text/markdown"
				}
			}
		}
	}
}